pydysofu/__init__.py
pydysofu/config.py
pydysofu/core_fuzzers.py
pydysofu/find_lambda.py
pydysofu/fuzz_decorator.py
pydysofu/fuzz_weaver.py
pydysofu/workflow_transformer.py
PyDySoFu-0.1a3.dist-info/LICENSE
PyDySoFu-0.1a3.dist-info/METADATA
PyDySoFu-0.1a3.dist-info/WHEEL
PyDySoFu-0.1a3.dist-info/top_level.txt
PyDySoFu-0.1a3.dist-info/RECORD
