Metadata-Version: 2.1
Name: PyDySoFu
Version: 0.1a3
Summary: PYthon DYnamic SOurce code FUzzing -- an implementation of dynamic fuzzing in Python. (Researchware)
Home-page: http://probablytom.com/
Author: Tom Wallis and Tim Storer
Author-email: w.wallis.1@research.gla.ac.uk
License: MIT
Platform: UNKNOWN
Classifier: License :: OSI Approved :: MIT License
Classifier: Programming Language :: Python
Classifier: Programming Language :: Python :: 2
Classifier: Programming Language :: Python :: 2.7
Classifier: Programming Language :: Python :: Implementation :: CPython
Classifier: Programming Language :: Python :: Implementation :: PyPy
Requires-Python: <3
Requires-Dist: drawer
